<annotation>
	<folder>image</folder>
	<filename>car_(4).jpg</filename>
	<path>D:\python\image\car_(4).jpg</path>
	<source>
		<database>Unknown</database>
	</source>
	<size>
		<width>3456</width>
		<height>4608</height>
		<depth>3</depth>
	</size>
	<segmented>0</segmented>
	<object>
		<name>Car</name>
		<pose>Unspecified</pose>
		<truncated>0</truncated>
		<difficult>0</difficult>
		<bndbox>
			<xmin>111</xmin>
			<ymin>994</ymin>
			<xmax>3145</xmax>
			<ymax>3913</ymax>
		</bndbox>
	</object>
</annotation>