<annotation>
	<folder>image</folder>
	<filename>NMV_(35).jpg</filename>
	<path>D:\python\image\NMV_(35).jpg</path>
	<source>
		<database>Unknown</database>
	</source>
	<size>
		<width>650</width>
		<height>974</height>
		<depth>3</depth>
	</size>
	<segmented>0</segmented>
	<object>
		<name>MNV</name>
		<pose>Unspecified</pose>
		<truncated>0</truncated>
		<difficult>0</difficult>
		<bndbox>
			<xmin>119</xmin>
			<ymin>574</ymin>
			<xmax>428</xmax>
			<ymax>891</ymax>
		</bndbox>
	</object>
</annotation>