<annotation>
	<folder>image</folder>
	<filename>truck_(106).jpg</filename>
	<path>D:\python\image\truck_(106).jpg</path>
	<source>
		<database>Unknown</database>
	</source>
	<size>
		<width>3184</width>
		<height>1940</height>
		<depth>3</depth>
	</size>
	<segmented>0</segmented>
	<object>
		<name>Truck</name>
		<pose>Unspecified</pose>
		<truncated>0</truncated>
		<difficult>0</difficult>
		<bndbox>
			<xmin>269</xmin>
			<ymin>188</ymin>
			<xmax>3079</xmax>
			<ymax>1907</ymax>
		</bndbox>
	</object>
</annotation>